waveinfo-0.5.0.dist-info/METADATA
waveinfo-0.5.0.dist-info/WHEEL
waveinfo-0.5.0.dist-info/licenses/LICENSE
waveinfo.libs/libgcc_s-39080030.so.1
waveinfo/__init__.py
waveinfo/__init__.pyi
waveinfo/py.typed
waveinfo/waveinfo.cpython-310-aarch64-linux-gnu.so
waveinfo-0.5.0.dist-info/RECORD
