Metadata-Version: 2.4
Name: waveinfo
Version: 0.5.0
Classifier: Programming Language :: Rust
Classifier: Programming Language :: Python :: Implementation :: CPython
Classifier: Programming Language :: Python :: Implementation :: PyPy
Classifier: License :: OSI Approved :: MIT License
Classifier: Development Status :: 4 - Beta
Requires-Dist: mkdocs ; extra == 'docs'
Requires-Dist: mkdocstrings[python] ; extra == 'docs'
Provides-Extra: docs
License-File: LICENSE
Summary: A package to read wave audio files and expose details of their contents.
Keywords: wave,wav,audio
Author: Bruce Cutler
Requires-Python: >=3.8
Project-URL: Homepage, https://py-waveinfo.readthedocs.io
Project-URL: Documentation, https://py-waveinfo.readthedocs.io/en/stable
Project-URL: Repository, https://github.com/sumebrius/py-waveinfo
